AUTHORS
ChangeLog
LICENSE
README.md
requirements.txt
setup.cfg
setup.py
tox.ini
images/quincy.jpg
quincy/__init__.py
quincy/api.py
quincy/common.py
quincy/jsonutil.py
quincy/v1_api.py
quincy/v1_impl.py
quincy/v2_api.py
quincy/v2_impl.py
quincy.egg-info/PKG-INFO
quincy.egg-info/SOURCES.txt
quincy.egg-info/dependency_links.txt
quincy.egg-info/not-zip-safe
quincy.egg-info/pbr.json
quincy.egg-info/requires.txt
quincy.egg-info/top_level.txt